pyhasse.chain-0.3.0-py3.7-nspkg.pth
pyhasse/chain/__init__.py
pyhasse/chain/calc.py
pyhasse.chain-0.3.0.dist-info/AUTHORS.rst
pyhasse.chain-0.3.0.dist-info/AUTHORS.rst~
pyhasse.chain-0.3.0.dist-info/LICENSE
pyhasse.chain-0.3.0.dist-info/METADATA
pyhasse.chain-0.3.0.dist-info/WHEEL
pyhasse.chain-0.3.0.dist-info/namespace_packages.txt
pyhasse.chain-0.3.0.dist-info/top_level.txt
pyhasse.chain-0.3.0.dist-info/RECORD
