Metadata-Version: 2.1
Name: pyhasse.chain
Version: 0.3.0
Summary: pyhasse.chain: TODO
Home-page: https://pyhasse.org
Author: Rainer Bruggemann
Author-email: rainer.bruggemann@pyhasse.org
License: MIT license
Download-URL: https://gitlab.com/pyhasse/chain/
Keywords: chain
Platform: UNKNOWN
Classifier: Development Status :: 2 - Pre-Alpha
Classifier: Intended Audience :: Developers
Classifier: Intended Audience :: Science/Research
Classifier: Topic :: Scientific/Engineering :: Mathematics
Classifier: License :: OSI Approved :: MIT License
Classifier: Natural Language :: English
Classifier: Programming Language :: Python :: 3.7
Requires-Dist: setuptools
Requires-Dist: pyhasse.core
